rustic_ai/lancedb/__init__.py
rustic_ai/lancedb/kbindex_backend_lancedb.py
rusticai_lancedb-1.0.0.dist-info/METADATA
rusticai_lancedb-1.0.0.dist-info/WHEEL
rusticai_lancedb-1.0.0.dist-info/RECORD
