Metadata-Version: 2.4
Name: rusticai-lancedb
Version: 1.0.0
Summary: Support for LanceDB backend KnowledgeBase
License-Expression: Apache-2.0
Author: Dragonscale Industries Inc.
Author-email: dev@dragonscale.ai
Requires-Python: >=3.12,<3.13
Classifier: Programming Language :: Python :: 3
Classifier: Programming Language :: Python :: 3.12
Provides-Extra: test
Requires-Dist: lancedb (>=0.25.0,<0.26.0)
Requires-Dist: rusticai-core (>=1.0.0,<1.1.0)
Project-URL: Homepage, https://www.rustic.ai/
Project-URL: Repository, https://github.com/dragonscale-ai/rustic-ai
Project-URL: Rustic AI Core, https://pypi.org/project/rusticai-core/
